stracking/__init__.py
stracking/cli/__init__.py
stracking/cli/detector_dog.py
stracking/cli/detector_doh.py
stracking/cli/detector_log.py
stracking/cli/linker_shortest_path.py
stracking/containers/__init__.py
stracking/containers/_containers.py
stracking/data/__init__.py
stracking/data/fake_tracks1.tif
stracking/data/tracks1_3d/track1_t001.tif
stracking/data/tracks1_3d/track1_t002.tif
stracking/data/tracks1_3d/track1_t003.tif
stracking/data/tracks1_3d/track1_t004.tif
stracking/data/tracks1_3d/track1_t005.tif
stracking/detectors/__init__.py
stracking/detectors/_detector.py
stracking/detectors/_gaussian_detectors.py
stracking/detectors/_seg_detector.py
stracking/detectors/tests/__init__.py
stracking/detectors/tests/test_gaussian_detectors.py
stracking/detectors/tests/tracks1.tif
stracking/detectors/tests/tracks1_crop.tif
stracking/features/__init__.py
stracking/features/_feature.py
stracking/features/_length.py
stracking/features/tests/__init__.py
stracking/features/tests/test_length.py
stracking/filters/__init__.py
stracking/filters/_feature_filter.py
stracking/filters/_filter.py
stracking/filters/tests/__init__.py
stracking/filters/tests/test_feature_filter.py
stracking/io/__init__.py
stracking/io/_csv_io.py
stracking/io/_icy_io.py
stracking/io/_io.py
stracking/io/_isbi_io.py
stracking/io/_particles_io.py
stracking/io/_reader_function.py
stracking/io/_st_io.py
stracking/io/_trackmate_io.py
stracking/io/tests/__init__.py
stracking/io/tests/test_reader.py
stracking/linkers/__init__.py
stracking/linkers/_euclidean_cost.py
stracking/linkers/_linker.py
stracking/linkers/_nn_linker.py
stracking/linkers/_sp_linker.py
stracking/linkers/utils.py
stracking/linkers/tests/__init__.py
stracking/linkers/tests/test_sp_linker.py
stracking/observers/__init__.py
stracking/observers/_observers.py
stracking/pipelines/__init__.py
stracking/pipelines/_pipeline.py
stracking/properties/__init__.py
stracking/properties/_intensity.py
stracking/properties/_properties.py
stracking-0.1.10.dist-info/LICENSE
stracking-0.1.10.dist-info/METADATA
stracking-0.1.10.dist-info/WHEEL
stracking-0.1.10.dist-info/entry_points.txt
stracking-0.1.10.dist-info/top_level.txt
stracking-0.1.10.dist-info/RECORD
