Metadata-Version: 2.1
Name: stracking
Version: 0.1.10
Summary: Implementation of particle tracking algorithms for 2D+t and 3D+t scientific data
Home-page: https://github.com/sylvainprigent/stracking
Author: Sylvain Prigent
Author-email: meriadec.prigent@gmail.com
License: BSD 3-Clause
Classifier: Development Status :: 2 - Pre-Alpha
Classifier: Intended Audience :: Developers
Classifier: Topic :: Software Development :: Testing
Classifier: Programming Language :: Python
Classifier: Programming Language :: Python :: 3
Classifier: Programming Language :: Python :: 3.9
Classifier: Operating System :: OS Independent
Classifier: License :: OSI Approved :: BSD License
Requires-Python: >=3.7
License-File: LICENSE
Requires-Dist: scipy >=1.6.3
Requires-Dist: scikit-image >=0.18.1
Requires-Dist: pandas >=1.2.4
